{
    "boxShadow": "none",
    "widgetName": "Input1Copy",
    "dynamicPropertyPathList": [],
    "displayName": "Input",
    "iconSVG": "/static/media/icon.9f505595da61a34f563dba82adeb06ec.svg",
    "searchTags": [
        "form",
        "text input",
        "number",
        "textarea"
    ],
    "topRow": 6,
    "bottomRow": 13,
    "parentRowSpace": 10,
    "labelWidth": 5,
    "autoFocus": false,
    "type": "INPUT_WIDGET_V2",
    "hideCard": false,
    "animateLoading": true,
    "parentColumnSpace": 6.48583984375,
    "dynamicTriggerPathList": [{"key": "onTextChanged"}],
    "resetOnSubmit": true,
    "leftColumn": 2,
    "dynamicBindingPathList": [
        {"key": "accentColor"},
        {"key": "borderRadius"}
    ],
    "labelPosition": "Top",
    "labelStyle": "",
    "inputType": "PASSWORD",
    "isDisabled": false,
    "key": "rcoz8754yy",
    "labelTextSize": "0.875rem",
    "isRequired": false,
    "onTextChanged": "apps",
    "isDeprecated": false,
    "rightColumn": 63,
    "dynamicHeight": "FIXED",
    "widgetId": "42v563sbyf",
    "accentColor": "{{appsmith.theme.colors.primaryColor}}",
    "showStepArrows": false,
    "isVisible": true,
    "label": "New password",
    "version": 2,
    "parentId": "91dl5hbj4u",
    "labelAlignment": "left",
    "renderMode": "CANVAS",
    "isLoading": false,
    "borderRadius": "{{appsmith.theme.borderRadius.appBorderRadius}}",
    "maxDynamicHeight": 9000,
    "iconAlign": "left",
    "defaultText": "",
    "minDynamicHeight": 4
}